keycred/__init__.py
keycred/main.py
keycred-0.1.2.dist-info/WHEEL
keycred-0.1.2.dist-info/METADATA
keycred-0.1.2.dist-info/RECORD
