Metadata-Version: 2.1
Name: keycred
Version: 0.1.2
Summary: Thin wrapper for PyKeePass - a class Credentials to handle it.
Author: Gwang-Jin Kim
Author-email: gwang.jin.kim.phd@gmail.com
Requires-Python: >=3.7,<4.0
Classifier: Programming Language :: Python :: 3
Classifier: Programming Language :: Python :: 3.10
Classifier: Programming Language :: Python :: 3.7
Classifier: Programming Language :: Python :: 3.8
Classifier: Programming Language :: Python :: 3.9
Requires-Dist: pycryptaes (>=0.1.4,<0.2.0)
Requires-Dist: pykeepass (>=4.0.3,<5.0.0)
